statistique.py
statistique-0.0.1.dist-info/LICENSE
statistique-0.0.1.dist-info/METADATA
statistique-0.0.1.dist-info/WHEEL
statistique-0.0.1.dist-info/top_level.txt
statistique-0.0.1.dist-info/RECORD
