Metadata-Version: 2.1
Name: statistique
Version: 0.0.1
Summary: Librarie pour le calculs statistiques
Author: Factis-Nuza
Classifier: Programming Language :: Python :: 3
Classifier: License :: OSI Approved :: MIT License
Classifier: Operating System :: OS Independent
Requires-Python: >3.6
License-File: LICENSE
